okfinance/OkDb.py
okfinance/OkStock.py
okfinance/OkThs.py
okfinance/__init__.py
okfinance/ths.min.js
okfinance/js/ths.min.js
okfinance-1.2.4.dist-info/LICENSE
okfinance-1.2.4.dist-info/METADATA
okfinance-1.2.4.dist-info/WHEEL
okfinance-1.2.4.dist-info/top_level.txt
okfinance-1.2.4.dist-info/RECORD
