Metadata-Version: 2.1
Name: okfinance
Version: 1.2.4
Summary: 金融工具库
Home-page: https://github.com/youxikaifa/finance
Author: Langzijin
Author-email: 1023142580@qq.com
License: UNKNOWN
Platform: UNKNOWN
Classifier: Programming Language :: Python :: 2
Classifier: License :: OSI Approved :: MIT License
Classifier: Operating System :: OS Independent
Requires-Python: >=2.7
License-File: LICENSE
